{"pres":{"pontosRP":-44,"tipo":"Plenário","sessoes":151,"presenca":128,"just":4,"njust":19},"proc":{"processos":[],"pontosRP":0},"priv":{"anos":[{"ano":"\n                                2018\n                            ","valor":90000.1},{"ano":"\n                                2017\n                            ","valor":295880.27}],"pontosRP":42},"legs":{"leis":[{"id":"13939","nome":"MPV 752/2016 - Licitações e contratos","voto":1,"valor":15},{"id":"14671","nome":"PDC 886/2018 - Intervenção federal no RJ","voto":1,"valor":15},{"id":"14606","nome":"PL 8703/2017 - Votação Nominal para Fundão","voto":1,"valor":30},{"id":"14607","nome":"PL 8703/2017 - Fundão Eleitoral","voto":-1,"valor":-30},{"id":"14559","nome":"PL 5587/2016 - Uber - Câmara","voto":1,"valor":20}],"pontosRP":110},"outr":{"criterios":[{"descr":"Formação (Políticos com formação universitária ganham cinco pontos adicionais)","valor":5},{"descr":"Filiações partidárias (Políticos que tenham permanecido sempre no mesmo partido ganham dez pontos. A partir de dois partidos, a cada mudança perde dez pontos.)","valor":10}],"pontosRP":15},"info":[{"nome":"Nome","valor":"YEDA RORATO CRUSIUS"},{"nome":"Apelido","valor":"YEDA CRUSIUS"},{"nome":"E-mail","valor":"dep.yedacrusius@camara.gov.br"},{"nome":"CPF","valor":"154.198.190-15"},{"nome":"Data de Nascimento","valor":"26/07/1944"},{"nome":"Partido","valor":"Partido da Social Democracia Brasileira"},{"nome":"Outras Informações","valor":"YEDA CRUSIUS"},{"nome":"Formação Acadêmica","valor":"Superior"},{"nome":"Profissão","valor":"Economista, Professor(a)"},{"nome":"Estado","valor":"Rio Grande do Sul"},{"nome":"Filiações Partidárias","valor":"PSDB"},{"nome":"Orgão","valor":"Câmara dos Deputados/BR"},{"nome":"Cargo","valor":"Deputado Federal"}]}